{
 "metadata": {
  "keywords": "",
  "robots": "index",
  "description": "",
  "title": "",
  "image": []
 },
 "mdx": {
  "altBody": "",
  "status": "rdmd"
 },
 "api": {
  "results": {
   "codes": [
    {
     "status": 200,
     "language": "json",
     "code": "{}",
     "name": ""
    },
    {
     "status": 400,
     "language": "json",
     "code": "{}",
     "name": ""
    }
   ]
  },
  "auth": "required",
  "params": [],
  "url": "",
  "method": "get"
 },
 "next": {
  "pages": [],
  "description": ""
 },
 "algolia": {
  "translationFailure": false,
  "publishPending": false,
  "recordCount": 1,
  "updatedAt": "2023-02-21T19:16:06.671Z"
 },
 "icon": "",
 "deprecated": false,
 "reusableContent": [],
 "revision": 1,
 "_id": "63f5176df91c7700118e7812",
 "version": "63f5176df91c7700118e7825",
 "updatedAt": "2019-11-27T22:20:14.855Z",
 "createdAt": "2019-11-07T13:37:25.809Z",
 "project": "5daf2e65f4109c0040fd51e1",
 "user": "5b8400d7185d5e00036dcc3b",
 "category": "63f5176df91c7700118e77a3",
 "updates": [],
 "link_external": true,
 "link_url": "https://docs.dash.org/en/stable/developers/integration.html#sdk-resources",
 "sync_unique": "",
 "hidden": false,
 "isReference": false,
 "order": 5,
 "body": "",
 "excerpt": "",
 "slug": "additional-resources-sdk-resources",
 "type": "link",
 "title": "SDK Resources",
 "__v": 0,
 "parentDoc": null,
 "pendingAlgoliaPublish": false,
 "previousSlug": "",
 "slugUpdatedAt": "2021-03-03T23:25:01.681Z",
 "isApi": false,
 "id": "63f5176df91c7700118e7812",
 "body_html": ""
}