{
 "pendingAlgoliaPublish": false, 
 "parentDoc": null, 
 "excerpt": "", 
 "api": {
  "url": "", 
  "params": [], 
  "method": "get", 
  "auth": "required", 
  "results": {
   "codes": [
    {
     "status": 200, 
     "code": "{}", 
     "name": "", 
     "language": "json"
    }, 
    {
     "status": 400, 
     "code": "{}", 
     "name": "", 
     "language": "json"
    }
   ]
  }
 }, 
 "previousSlug": "", 
 "updatedAt": "2019-10-28T15:48:28.060Z", 
 "id": "5e96055329a18c0025d3923b", 
 "sync_unique": "", 
 "isApi": false, 
 "createdAt": "2019-10-28T15:44:50.945Z", 
 "category": "5e96055329a18c0025d391e3", 
 "title": "Block Chain", 
 "next": {
  "description": "", 
  "pages": [
   {
    "category": "Core Guides", 
    "icon": "file-text-o", 
    "type": "doc", 
    "slug": "core-guide-block-chain-block-chain-overview", 
    "name": "Block Chain Overview"
   }, 
   {
    "category": "Core Guides", 
    "slug": "core-guide-block-chain-proof-of-work", 
    "type": "doc", 
    "name": "Proof Of Work", 
    "icon": "file-text-o"
   }, 
   {
    "category": "Core Guides", 
    "slug": "core-guide-block-chain-block-height-and-forking", 
    "type": "doc", 
    "name": "Block Height and Forking", 
    "icon": "file-text-o"
   }, 
   {
    "category": "Core Guides", 
    "slug": "core-guide-block-chain-transaction-data", 
    "type": "doc", 
    "name": "Transaction Data", 
    "icon": "file-text-o"
   }, 
   {
    "category": "Core Guides", 
    "slug": "core-guide-block-chain-consensus-rule-changes", 
    "type": "doc", 
    "name": "Consensus Rule Changes", 
    "icon": "file-text-o"
   }
  ]
 }, 
 "version": "5e96055329a18c0025d39261", 
 "slugUpdatedAt": "2021-02-17T04:17:01.458Z", 
 "hidden": false, 
 "type": "basic", 
 "metadata": {
  "image": [], 
  "description": "", 
  "title": ""
 }, 
 "body": "The block chain provides Dash's public ledger, an ordered and timestamped record of transactions. This system is used to protect against double spending and modification of previous transaction records.\n\nEach full node in the Dash network independently stores a block chain containing only blocks validated by that node. When several nodes all have the same blocks in their block chain, they are considered to be in <<glossary:consensus>>. The validation rules these nodes follow to maintain consensus are called <<glossary:consensus rules>>. This section describes many of the consensus rules used by Dash Core.", 
 "link_external": false, 
 "body_html": "<div class=\"magic-block-textarea\"><p>The block chain provides Dash&#39;s public ledger, an ordered and timestamped record of transactions. This system is used to protect against double spending and modification of previous transaction records.</p>\n<p>Each full node in the Dash network independently stores a block chain containing only blocks validated by that node. When several nodes all have the same blocks in their block chain, they are considered to be in &lt;&lt;glossary:consensus&gt;&gt;. The validation rules these nodes follow to maintain consensus are called &lt;&lt;glossary:consensus rules&gt;&gt;. This section describes many of the consensus rules used by Dash Core.</p>\n\n</div>", 
 "updates": [], 
 "isReference": false, 
 "slug": "core-guide-block-chain", 
 "link_url": "", 
 "project": "5daf2e65f4109c0040fd51e1", 
 "__v": 4, 
 "_id": "5e96055329a18c0025d3923b", 
 "order": 2, 
 "user": "5b8400d7185d5e00036dcc3b"
}