{
 "metadata": {
  "keywords": "",
  "robots": "index",
  "description": "",
  "image": [],
  "title": ""
 },
 "mdx": {
  "altBody": "",
  "status": "rdmd"
 },
 "api": {
  "method": "get",
  "url": "",
  "auth": "required",
  "results": {
   "codes": [
    {
     "name": "",
     "code": "{}",
     "language": "json",
     "status": 200
    },
    {
     "name": "",
     "code": "{}",
     "language": "json",
     "status": 400
    }
   ]
  },
  "params": [],
  "examples": {
   "codes": []
  }
 },
 "next": {
  "description": "",
  "pages": []
 },
 "algolia": {
  "translationFailure": false,
  "publishPending": false,
  "recordCount": 2,
  "updatedAt": "2023-09-06T16:36:51.076Z"
 },
 "reusableContent": [],
 "_id": "64f8a9df750465004742adeb",
 "title": "Dash platform applications",
 "icon": "",
 "updates": [],
 "type": "basic",
 "slug": "dash-sdk-getting-started-dash-platform-applications",
 "excerpt": "",
 "body": "## DPNS\n\nDPNS is handled in the Dash SDK Client under the namespace `client.platform.names.*'`. [Read more here](https://dashplatform.readme.io/docs/dash-sdk-names)\n\n## DashPay\n\nThe DashPay contract is registered on testnet under contract id `Bwr4WHCPz5rFVAD87RqTs3izo4zpzwsEdKPWUT1NS1C7`. Its functionality is not incorporated with the Dash SDK at this time.",
 "order": 2,
 "isReference": false,
 "deprecated": false,
 "hidden": false,
 "sync_unique": "",
 "link_url": "",
 "link_external": false,
 "previousSlug": "dash-platform-applications",
 "slugUpdatedAt": "2023-07-17T21:39:25.178Z",
 "revision": 8,
 "user": "62b2101422da70001ee51d95",
 "project": "5bda01cad172e200499a20a9",
 "parentDoc": "64f8a9df750465004742ade8",
 "category": "64f8a9df750465004742ad74",
 "createdAt": "2023-07-13T15:16:13.929Z",
 "updatedAt": "2023-07-18T14:07:31.839Z",
 "version": "64f8a9df750465004742ae1d",
 "__v": 1,
 "isApi": false,
 "id": "64f8a9df750465004742adeb",
 "body_html": "<h2 class=\"heading heading-2 header-scroll\" align=\"\"><div class=\"heading-anchor anchor waypoint\" id=\"dpns\"></div><div class=\"heading-text\"><div id=\"section-dpns\" class=\"heading-anchor_backwardsCompatibility\"></div>DPNS</div><a aria-label=\"Skip link to DPNS\" class=\"heading-anchor-icon fa fa-anchor\" href=\"#dpns\"></a></h2>\n<p>DPNS is handled in the Dash SDK Client under the namespace <button aria-label=\"Copy Code\" class=\"rdmd-code-copy fa\"></button><code class=\"rdmd-code lang- theme-light\" data-lang=\"\" name=\"\" tabindex=\"0\">client.platform.names.*&#x27;</code>. <a href=\"https://dashplatform.readme.io/docs/dash-sdk-names\" target=\"\" title=\"\">Read more here</a></p>\n<h2 class=\"heading heading-2 header-scroll\" align=\"\"><div class=\"heading-anchor anchor waypoint\" id=\"dashpay\"></div><div class=\"heading-text\"><div id=\"section-dash-pay\" class=\"heading-anchor_backwardsCompatibility\"></div>DashPay</div><a aria-label=\"Skip link to DashPay\" class=\"heading-anchor-icon fa fa-anchor\" href=\"#dashpay\"></a></h2>\n<p>The DashPay contract is registered on testnet under contract id <button aria-label=\"Copy Code\" class=\"rdmd-code-copy fa\"></button><code class=\"rdmd-code lang- theme-light\" data-lang=\"\" name=\"\" tabindex=\"0\">Bwr4WHCPz5rFVAD87RqTs3izo4zpzwsEdKPWUT1NS1C7</code>. Its functionality is not incorporated with the Dash SDK at this time.</p>"
}