{
 "metadata": {
  "image": [],
  "title": "",
  "description": ""
 },
 "api": {
  "method": "get",
  "url": "",
  "auth": "required",
  "results": {
   "codes": [
    {
     "status": 200,
     "language": "json",
     "code": "{}",
     "name": ""
    },
    {
     "status": 400,
     "language": "json",
     "code": "{}",
     "name": ""
    }
   ]
  },
  "params": []
 },
 "next": {
  "description": "",
  "pages": []
 },
 "algolia": {
  "recordCount": 1,
  "publishPending": false,
  "updatedAt": "2023-09-06T16:36:32.000Z"
 },
 "title": "Core (Layer 1 Protocol)",
 "icon": "",
 "updates": [],
 "type": "link",
 "slug": "resources-source-code-core-blockchain",
 "excerpt": "",
 "body": "",
 "order": 8,
 "isReference": false,
 "deprecated": false,
 "hidden": false,
 "sync_unique": "",
 "link_url": "https://github.com/dashpay/dash",
 "link_external": true,
 "previousSlug": "",
 "slugUpdatedAt": "2023-10-19T19:28:55.105Z",
 "revision": 1,
 "_id": "64f8a9df750465004742ad83",
 "version": "64f8a9df750465004742ae1d",
 "updatedAt": "2019-12-24T21:22:11.281Z",
 "createdAt": "2019-08-01T13:39:55.864Z",
 "project": "5bda01cad172e200499a20a9",
 "category": "64f8a9df750465004742ad6f",
 "user": "5b8400d7185d5e00036dcc3b",
 "parentDoc": "64f8a9df750465004742ad82",
 "__v": 0,
 "isApi": false,
 "id": "64f8a9df750465004742ad83",
 "body_html": "&nbsp;"
}