{
 "pendingAlgoliaPublish": false, 
 "parentDoc": "60906294cda2820061269591", 
 "excerpt": "", 
 "api": {
  "url": "", 
  "params": [], 
  "method": "get", 
  "auth": "required", 
  "results": {
   "codes": [
    {
     "status": 200, 
     "code": "{}", 
     "name": "", 
     "language": "json"
    }, 
    {
     "status": 400, 
     "code": "{}", 
     "name": "", 
     "language": "json"
    }
   ]
  }
 }, 
 "previousSlug": "", 
 "updatedAt": "2019-12-24T00:34:59.017Z", 
 "id": "60906294cda28200612695b6", 
 "sync_unique": "", 
 "isApi": false, 
 "createdAt": "2019-12-24T00:34:59.017Z", 
 "category": "60906294cda2820061269580", 
 "title": "DPNS Client", 
 "next": {
  "description": "", 
  "pages": []
 }, 
 "version": "60906294cda28200612695e5", 
 "slugUpdatedAt": "2021-08-03T22:12:29.189Z", 
 "hidden": false, 
 "type": "link", 
 "metadata": {
  "image": [], 
  "description": "", 
  "title": ""
 }, 
 "body": "", 
 "link_external": true, 
 "body_html": "&nbsp;", 
 "user": "5b8400d7185d5e00036dcc3b", 
 "isReference": false, 
 "slug": "resources-source-code-dpns-client", 
 "link_url": "https://github.com/dashevo/js-dpns-client", 
 "project": "5bda01cad172e200499a20a9", 
 "__v": 0, 
 "_id": "60906294cda28200612695b6", 
 "order": 5, 
 "updates": []
}